manipulating/__init__.py
manipulating/manipulating.py
manipulating-1.0.dist-info/METADATA
manipulating-1.0.dist-info/WHEEL
manipulating-1.0.dist-info/licenses/LICENSE.txt
manipulating-1.0.dist-info/RECORD
