Metadata-Version: 2.3
Name: manipulating
Version: 1.0
Summary: Python string manipulation
Author-email: Joseph Spracklen <joseph.spracklen@my.utsa.edu>
License-File: LICENSE.txt
Classifier: License :: OSI Approved :: MIT License
Classifier: Operating System :: OS Independent
Classifier: Programming Language :: Python :: 3
Requires-Python: >=3.8
